llama_index/tools/duckduckgo/__init__.py
llama_index/tools/duckduckgo/base.py
llama_index_tools_duckduckgo-0.4.1.dist-info/METADATA
llama_index_tools_duckduckgo-0.4.1.dist-info/WHEEL
llama_index_tools_duckduckgo-0.4.1.dist-info/licenses/LICENSE
llama_index_tools_duckduckgo-0.4.1.dist-info/RECORD
