Metadata-Version: 2.4
Name: llama-index-tools-duckduckgo
Version: 0.4.1
Summary: llama-index tools integrating DuckDuckGo search
Author-email: Your Name <you@example.com>
Maintainer: leehuwuj
License-Expression: MIT
License-File: LICENSE
Keywords: research
Requires-Python: <4.0,>=3.9
Requires-Dist: duckduckgo-search<7,>=6.1.0
Requires-Dist: llama-index-core<0.15,>=0.13.0
